imder/__init__.py
imder/api.py
imder/cli.py
imder/core.py
imder-1.0.2.dist-info/METADATA
imder-1.0.2.dist-info/WHEEL
imder-1.0.2.dist-info/entry_points.txt
imder-1.0.2.dist-info/RECORD
