Metadata-Version: 2.4
Name: imder
Version: 1.0.2
Summary: Image and video pixel blending processor
Requires-Python: >=3.8
Requires-Dist: numpy>=1.21.0
Requires-Dist: opencv-python>=4.5.0
Requires-Dist: pillow>=9.0.0
Requires-Dist: pyfiglet>=0.8.0
